GccBianyiqi30FenzhongRumenjiaochengCYuyanZhongwenwang/README.md
GccBianyiqi30FenzhongRumenjiaochengCYuyanZhongwenwang/__init__.py
GccBianyiqi30FenzhongRumenjiaochengCYuyanZhongwenwang/__main__.py
GccBianyiqi30FenzhongRumenjiaochengCYuyanZhongwenwang/file.epub
GccBianyiqi30FenzhongRumenjiaochengCYuyanZhongwenwang/index.html
GccBianyiqi30FenzhongRumenjiaochengCYuyanZhongwenwang/css/__init__.py
GccBianyiqi30FenzhongRumenjiaochengCYuyanZhongwenwang/css/annotations.css
GccBianyiqi30FenzhongRumenjiaochengCYuyanZhongwenwang/css/main.css
GccBianyiqi30FenzhongRumenjiaochengCYuyanZhongwenwang/css/normalize.css
GccBianyiqi30FenzhongRumenjiaochengCYuyanZhongwenwang/css/popup.css
GccBianyiqi30FenzhongRumenjiaochengCYuyanZhongwenwang/font/__init__.py
GccBianyiqi30FenzhongRumenjiaochengCYuyanZhongwenwang/font/fontello.eot
GccBianyiqi30FenzhongRumenjiaochengCYuyanZhongwenwang/font/fontello.svg
GccBianyiqi30FenzhongRumenjiaochengCYuyanZhongwenwang/font/fontello.ttf
GccBianyiqi30FenzhongRumenjiaochengCYuyanZhongwenwang/font/fontello.woff
GccBianyiqi30FenzhongRumenjiaochengCYuyanZhongwenwang/img/__init__.py
GccBianyiqi30FenzhongRumenjiaochengCYuyanZhongwenwang/img/annotator-glyph-sprite.png
GccBianyiqi30FenzhongRumenjiaochengCYuyanZhongwenwang/img/annotator-icon-sprite.png
GccBianyiqi30FenzhongRumenjiaochengCYuyanZhongwenwang/img/apple-touch-icon.png
GccBianyiqi30FenzhongRumenjiaochengCYuyanZhongwenwang/img/cancelfullscreen.png
GccBianyiqi30FenzhongRumenjiaochengCYuyanZhongwenwang/img/close.png
GccBianyiqi30FenzhongRumenjiaochengCYuyanZhongwenwang/img/fullscreen.png
GccBianyiqi30FenzhongRumenjiaochengCYuyanZhongwenwang/img/loader.gif
GccBianyiqi30FenzhongRumenjiaochengCYuyanZhongwenwang/img/menu-icon.png
GccBianyiqi30FenzhongRumenjiaochengCYuyanZhongwenwang/img/save.png
GccBianyiqi30FenzhongRumenjiaochengCYuyanZhongwenwang/img/saved.png
GccBianyiqi30FenzhongRumenjiaochengCYuyanZhongwenwang/img/settings-s.png
GccBianyiqi30FenzhongRumenjiaochengCYuyanZhongwenwang/img/settings.png
gcc_bianyiqi_30_fenzhong_rumenjiaocheng_c_yuyan_zhongwenwang-2024.3.5.0.dist-info/METADATA
gcc_bianyiqi_30_fenzhong_rumenjiaocheng_c_yuyan_zhongwenwang-2024.3.5.0.dist-info/WHEEL
gcc_bianyiqi_30_fenzhong_rumenjiaocheng_c_yuyan_zhongwenwang-2024.3.5.0.dist-info/entry_points.txt
gcc_bianyiqi_30_fenzhong_rumenjiaocheng_c_yuyan_zhongwenwang-2024.3.5.0.dist-info/top_level.txt
gcc_bianyiqi_30_fenzhong_rumenjiaocheng_c_yuyan_zhongwenwang-2024.3.5.0.dist-info/RECORD
